object_store_py-0.2.0b1.dist-info/METADATA
object_store_py-0.2.0b1.dist-info/WHEEL
obstore.libs/libgcc_s-1e52349c.so.1
obstore/_list.pyi
obstore/store/_aws.pyi
obstore/store/_gcs.pyi
obstore/store/_client.pyi
obstore/store/_azure.pyi
obstore/store/_http.pyi
obstore/store/_retry.pyi
obstore/store/__init__.pyi
obstore/_obstore.pyi
obstore/_rename.pyi
obstore/_sign.pyi
obstore/_get.pyi
obstore/_delete.pyi
obstore/_head.pyi
obstore/exceptions.pyi
obstore/_copy.pyi
obstore/__init__.py
obstore/_put.pyi
obstore/_attributes.pyi
obstore/_obstore.pypy39-pp73-x86_64-linux-gnu.so
object_store_py-0.2.0b1.dist-info/RECORD
