Metadata-Version: 2.3
Name: object-store-py
Version: 0.2.0b1
Classifier: Programming Language :: Rust
Classifier: Programming Language :: Python :: Implementation :: CPython
Classifier: Programming Language :: Python :: Implementation :: PyPy
Summary: A Python interface to the Rust object_store crate, providing a uniform API for interacting with object storage services and local files.
Keywords: python
Home-Page: https://developmentseed.org/obstore
Author: Kyle Barron <kyle@developmentseed.org>
Author-email: Kyle Barron <kyle@developmentseed.org>
License: MIT OR Apache-2.0
Requires-Python: >=3.9
Project-URL: Source Code, https://github.com/developmentseed/obstore
